wikidata_client/.DS_Store
wikidata_client/__init__.py
wikidata_client/__main__.py
wikidata_client/api.py
wikidata_client/cli.py
wikidata_client/constants.py
wikidata_client/properties.py
wikidata_client/py.typed
wikidata_client/version.py
wikidata_client-0.0.4.dist-info/licenses/LICENSE
wikidata_client-0.0.4.dist-info/WHEEL
wikidata_client-0.0.4.dist-info/entry_points.txt
wikidata_client-0.0.4.dist-info/METADATA
wikidata_client-0.0.4.dist-info/RECORD
